odoo/addons/sale_stock_secondary_unit/README.rst
odoo/addons/sale_stock_secondary_unit/__init__.py
odoo/addons/sale_stock_secondary_unit/__manifest__.py
odoo/addons/sale_stock_secondary_unit/i18n/de.po
odoo/addons/sale_stock_secondary_unit/i18n/es.po
odoo/addons/sale_stock_secondary_unit/i18n/it.po
odoo/addons/sale_stock_secondary_unit/i18n/sale_stock_secondary_unit.pot
odoo/addons/sale_stock_secondary_unit/i18n/zh_CN.po
odoo/addons/sale_stock_secondary_unit/models/__init__.py
odoo/addons/sale_stock_secondary_unit/models/stock_rule.py
odoo/addons/sale_stock_secondary_unit/readme/CONTRIBUTORS.md
odoo/addons/sale_stock_secondary_unit/readme/DESCRIPTION.md
odoo/addons/sale_stock_secondary_unit/readme/USAGE.md
odoo/addons/sale_stock_secondary_unit/static/description/icon.png
odoo/addons/sale_stock_secondary_unit/static/description/index.html
odoo/addons/sale_stock_secondary_unit/tests/__init__.py
odoo/addons/sale_stock_secondary_unit/tests/test_sale_stock_secondary_unit.py
odoo_addon_sale_stock_secondary_unit-18.0.1.0.0.2.dist-info/METADATA
odoo_addon_sale_stock_secondary_unit-18.0.1.0.0.2.dist-info/WHEEL
odoo_addon_sale_stock_secondary_unit-18.0.1.0.0.2.dist-info/top_level.txt
odoo_addon_sale_stock_secondary_unit-18.0.1.0.0.2.dist-info/RECORD
